{"load_summary": {}, "successes": {"count": 750, "rate": 7.075472, "prompt_len": {"mean": 0, "rate": 52501.742539}, "output_len": {"mean": 0, "rate": 7069.612403}, "queue_len": {"mean": 0}, "request_latency": {"mean": 42.420587, "median": 43.144654, "p90": 49.433962, "p99": 58.4375}, "time_to_first_token": {"mean": 0.647494, "median": 0.218804, "p90": 2.162088, "p99": 4.7825}, "time_per_output_token": {"mean": 0.041773, "median": 0.038007, "p90": 0.048669, "p99": 0.145901}, "kv_cache_usage_percentage": {"mean": 0.0, "median": 0.0, "p90": 0.0, "p99": 0.0}, "num_requests_swapped": {"mean": 0}, "num_preemptions_total": {"mean": 0}, "prefix_cache_hit_percent": {"mean": 68.64235039906816}}, "failures": {}}