{"load_summary": {}, "successes": {"count": 1470, "rate": 7.241379, "prompt_len": {"mean": 0, "rate": 57204.497695}, "output_len": {"mean": 0, "rate": 7246.160613}, "queue_len": {"mean": 0}, "request_latency": {"mean": 94.367245, "median": 92.765957, "p90": 203.173278, "p99": 236.317328}, "time_to_first_token": {"mean": 41.708717, "median": 50.483092, "p90": 133.396963, "p99": 157.339696}, "time_per_output_token": {"mean": 0.051194, "median": 0.037632, "p90": 0.048025, "p99": 0.604397}, "kv_cache_usage_percentage": {"mean": 0.0, "median": 0.0, "p90": 0.0, "p99": 0.0}, "num_requests_swapped": {"mean": 0}, "num_preemptions_total": {"mean": 0}, "prefix_cache_hit_percent": {"mean": 59.73779944693932}}, "failures": {}}